examples/sc/LT_simple_sv/target/src/Target.sv
/*
============================================================================
 File        : Target.sv
 Copyright (c) 2016-2021 IC Verimeter. All rights reserved.
               Licensed under the MIT License.
               See LICENSE file in the project root for full license information.
 Description : TCP/IP SystemVerilog SHUNT
               b_transport SystemC to SystemVerilog examle  -Target(client)
 ============================================================================
*/
`ifndef TARGET_SV
 `define TARGET_SV

module automatic Target(input reg clk_i);

   import shunt_dpi_pkg::*;

   int clk_cnt=0;
   /* verilator lint_off UNUSED */
   /* verilator lint_off UNDRIVEN */
   //MEM
   //logic [31:0] mem [0:255]=0;
   logic [31:0] mem_data=0;
   logic [31:0] mem_byte_enable=0;
   logic [31:0] mem_addr=0;
   logic        mem_we=0;
   //logic      mem_oe;
   logic [31:0] mem_q=0;

   bit          end_sim =0 ;
   bit          start_sim=0;
   bit          trnx_in_progress=0;
   int          clk_next;

   int          sockid =0;
   
   cs_tlm_generic_payload_header_t h;
   cs_tlm_axi3_extension_payload_header_t h_ext;
   cs_tlm_axi3_extension_payload_header_t h_ext_out;
   byte         data_in[4];
   byte         byte_enable_in[4];

   byte         data_out[4];
   byte         byte_enable_out[4];


   /* verilator lint_on UNDRIVEN */
   /* verilator lint_on UNUSED */

   initial   begin
      
      $display("TARGET: shunt_dpi_tlm_header_id()=%h",shunt_dpi_tlm_header_id());
      $display("TARGET: shunt_dpi_tlm_data_id()=%h", shunt_dpi_tlm_data_id());
      $display("TARGET: shunt_dpi_tlm_axi3_ext_id()=%h",shunt_dpi_tlm_axi3_ext_id());
      $display("TARGET: shunt_dpi_tlm_signal_id()=%h",shunt_dpi_tlm_signal_id());
          
      sockid = shunt_dpi_target_init(`MY_PORT,`MY_HOST);
      shunt_dpi_tlm_send_command(sockid,SHUNT_TLM_START_SIM);
      start_sim =1;
      h_ext_out.AxBURST = 0;
      h_ext_out.AxCACHE = 0;
      h_ext_out.AxID    = 11;
      h_ext_out.AxLEN   = 0;
      h_ext_out.AxLOCK  = 3;
      h_ext_out.AxPROT  = 0;
      h_ext_out.AxSIZE  = 0;
      h_ext_out.xRESP   = 3;
      h_ext_out.xSTRB   = 0;
   end

   memory  mem(.data(mem_data),.addr(mem_addr), .we(mem_we), .clk(clk_i), .q(mem_q));

   /* verilator lint_off WIDTH */
   assign mem_data = {data_in[3],data_in[2],data_in[1],data_in[0]};
   assign {data_out[3],data_out[2],data_out[1],data_out[0]} = mem_q;
   //assign mem_addr = h.address;
   //assign mem_data =  {>>{data_in}};

   always @(posedge clk_i) begin
      //if(trnx_in_progress) $display("\nTARGET : mem.ram[%0d]=%h mem_data=%h @%0d\n",h.address,mem.ram[h.address],mem_data,clk_cnt);
      if (end_sim)  begin
         $display("\nTARGET: SHUNT_TLM_END_SIM clk_cnt=%0d\n",clk_cnt);
         $finish;
      end
   end


   always @(posedge clk_i) begin

      if(start_sim) begin
         if(!trnx_in_progress) begin
            shunt_dpi_tlm_recv_gp_transport(sockid,h,data_in,byte_enable_in);
            shunt_dpi_tlm_gp_header_print (h,"TARGET: ");
            if(h.command != SHUNT_TLM_END_SIM) begin
               shunt_dpi_tlm_recv_axi3_header(sockid,h_ext);
               shunt_dpi_tlm_axi3_header_print (h_ext,"TRAGET: ");
               shunt_dpi_tlm_send_axi3_header (sockid,h_ext_out);   
            end
            /* verilator lint_off BLKSEQ */
            h.response_status = SHUNT_TLM_OK_RESPONSE;
            /* verilator lint_on BLKSEQ */
            trnx_in_progress <=1;
            clk_next <= clk_cnt;
         end

         //WRITE
         if(h.command == SHUNT_TLM_WRITE_COMMAND) begin
            mem_we   <=1;
            mem_addr <= h.address;
         end

         //READ
         if(h.command == SHUNT_TLM_READ_COMMAND)  begin
            mem_addr <= h.address;
         end

         //
         if (trnx_in_progress && clk_cnt>clk_next+1) begin
            shunt_dpi_tlm_send_gp_transport(sockid,h,data_out,byte_enable_out);
            mem_we   <=0;
            trnx_in_progress <=0;
         end
         //
         if(h.command == SHUNT_TLM_END_SIM)  begin
            end_sim   <=1;
            start_sim <=0;
            trnx_in_progress <=0;
         end

      end // if (start_sim)
      clk_cnt<=clk_cnt+1;
   end // always @ (posedge clk_i)

endmodule : Target

/* verilator lint_off DECLFILENAME */
module memory
  (
   input [31:0] data,
   input [31:0] addr,
   input we, clk,
   output [31:0] q
   );

   reg [31:0]      ram[255:0];

   /* verilator lint_off UNUSED */
   reg [31:0]      addr_reg;
   /* verilator lint_on UNUSED */

   initial begin
      for (int i = 0; i < 256; i++) begin
         ram[i] = 32'hAA000000 | ($random % 256);
         //$display("TARGET: ram[%0d]=%h\n",i,ram[i]);
         addr_reg = 0;
      end
   end

   always @ (posedge clk)
     begin
        // Write
        if (we) ram[addr] <= data;
        addr_reg <= addr;
     end

   assign q = ram[addr_reg];

endmodule : memory
/* verilator lint_on DECLFILENAME */

`endif //  `ifndef TARGET_SV

examples/sc/LT_simple_sv/makedir/top_sim_ref.vcd
$version Generated by VerilatedVcd $end
$date Sat Sep 12 10:03:47 2020
 $end
$timescale   1ps $end

 $scope module TOP $end
  $var wire  1 U clk_i $end
  $scope module Target $end
   $var wire  8 H byte_enable_in(0) [7:0] $end
   $var wire  8 I byte_enable_in(1) [7:0] $end
   $var wire  8 J byte_enable_in(2) [7:0] $end
   $var wire  8 K byte_enable_in(3) [7:0] $end
   $var wire  8 P byte_enable_out(0) [7:0] $end
   $var wire  8 Q byte_enable_out(1) [7:0] $end
   $var wire  8 R byte_enable_out(2) [7:0] $end
   $var wire  8 S byte_enable_out(3) [7:0] $end
   $var wire 32 % clk_cnt [31:0] $end
   $var wire  1 U clk_i $end
   $var wire 32 - clk_next [31:0] $end
   $var wire  8 D data_in(0) [7:0] $end
   $var wire  8 E data_in(1) [7:0] $end
   $var wire  8 F data_in(2) [7:0] $end
   $var wire  8 G data_in(3) [7:0] $end
   $var wire  8 L data_out(0) [7:0] $end
   $var wire  8 M data_out(1) [7:0] $end
   $var wire  8 N data_out(2) [7:0] $end
   $var wire  8 O data_out(3) [7:0] $end
   $var wire  1 * end_sim $end
   $var wire 704 . h [703:0] $end
   $var wire 32 ' mem_addr [31:0] $end
   $var wire 32 V mem_byte_enable [31:0] $end
   $var wire 32 & mem_data [31:0] $end
   $var wire 32 ) mem_q [31:0] $end
   $var wire  1 ( mem_we $end
   $var wire 32 # sockid [31:0] $end
   $var wire  1 + start_sim $end
   $var wire  1 , trnx_in_progress $end
   $scope module mem $end
    $var wire 32 ' addr [31:0] $end
    $var wire 32 T addr_reg [31:0] $end
    $var wire  1 U clk $end
    $var wire 32 & data [31:0] $end
    $var wire 32 ) q [31:0] $end
    $var wire  1 ( we $end
    $scope module unnamedblk1 $end
     $var wire 32 $ i [31:0] $end
    $upscope $end
   $upscope $end
  $upscope $end
 $upscope $end
$enddefinitions $end


#0
b00000000000000000000000000000100 #
b00000000000000000000000100000000 $
b00000000000000000000000000000000 %
b00000000000000000000000000000000 &
b00000000000000000000000000000000 '
0(
b10101010000000000000000000101111 )
0*
1+
0,
b00000000000000000000000000000000 -
b00000000000000000000000000000000000000000000000000000000000000000000000000000000000000000000000000000000000000000000000000000000000000000000000000000000000000000000000000000000000000000000000000000000000000000000000000000000000000000000000000000000000000000000000000000000000000000000000000000000000000000000000000000000000000000000000000000000000000000000000000000000000000000000000000000000000000000000000000000000000000000000000000000000000000000000000000000000000000000000000000000000000000000000000000000000000000000000000000000000000000000000000000000000000000000000000000000000000000000000000000000000000000000000000000000000000000000000000000000000000000000000000000000000000000000000000000000000 .
b00000000 D
b00000000 E
b00000000 F
b00000000 G
b00000000 H
b00000000 I
b00000000 J
b00000000 K
b00101111 L
b00000000 M
b00000000 N
b10101010 O
b00000000 P
b00000000 Q
b00000000 R
b00000000 S
b00000000000000000000000000000000 T
0U
b00000000000000000000000000000000 V
#1
b00000000000000000000000000000001 %
b00000000000000000000000000100000 '
1,
b00000000000000000000000000000000000000000000000000000000000000000000000000000000000000000000000000000000000000000000000000100000000000000000000000000000000000000000000000000000000000000000000000000000000000000000000000000000000000000000000000000000000001000000000000000000000000000000000000000000000000000000000000000000000000000000000000000000000000000000000000000000000000000000010000000000000000000000000000000000000000000000000000000000000000000000000000000000000000000000000000000000000000000000000000000001000000000000000000000000000000000000000000000000000000000000101000000000000000000000000000000000000000000000000000000000000000000000000000000000000000000000000000000000000000000000000000000000 .
1U
#2
0U
#3
b00000000000000000000000000000010 %
b10101010000000000000000001010011 )
b01010011 L
b00000000000000000000000000100000 T
1U
#4
0U
#5
b00000000000000000000000000000011 %
0,
1U
#6
0U
#7
b00000000000000000000000000000100 %
b10101010000000000000000001010011 &
b00000000000000000000000000100100 '
1,
b00000000000000000000000000000011 -
b00000000000000000000000000000000000000000000000000000000000000000000000000000000000000000000000000000000000000000000000000100100000000000000000000000000000000000000000000000000000000000000000000000000000000000000000000000000000000000000000000000000000001000000000000000000000000000000000000000000000000000000000000000000000000000000000000000000000000000000000000000000000000000000010000000000000000000000000000000000000000000000000000000000000000000000000000000000000000000000000000000000000000000000000000000001000000000000000000000000000000000000000000000000000000000000101000000000000000000000000000000000000000000000000000000000000000000000000000000000000000000000000000000000000000000000000000000000 .
b01010011 D
b10101010 G
1U
#8
0U
#9
b00000000000000000000000000000101 %
b10101010000000000000000010101010 )
b10101010 L
b00000000000000000000000000100100 T
1U
#10
0U
#11
b00000000000000000000000000000110 %
0,
1U
#12
0U
#13
b00000000000000000000000000000111 %
b10101010000000000000000010101010 &
b00000000000000000000000000101000 '
1,
b00000000000000000000000000000110 -
b00000000000000000000000000000000000000000000000000000000000000000000000000000000000000000000000000000000000000000000000000101000000000000000000000000000000000000000000000000000000000000000000000000000000000000000000000000000000000000000000000000000000001000000000000000000000000000000000000000000000000000000000000000000000000000000000000000000000000000000000000000000000000000000010000000000000000000000000000000000000000000000000000000000000000000000000000000000000000000000000000000000000000000000000000000001000000000000000000000000000000000000000000000000000000000000101000000000000000000000000000000000000000000000000000000000000000000000000000000000000000000000000000000000000000000000000000000000 .
b10101010 D
1U
#14
0U
#15
b00000000000000000000000000001000 %
b10101010000000000000000010000111 )
b10000111 L
b00000000000000000000000000101000 T
1U
#16
0U
#17
b00000000000000000000000000001001 %
0,
1U
#18
0U
#19
b00000000000000000000000000001010 %
b10101010000000000000000010000111 &
b00000000000000000000000000101100 '
1,
b00000000000000000000000000001001 -
b00000000000000000000000000000000000000000000000000000000000000000000000000000000000000000000000000000000000000000000000000101100000000000000000000000000000000000000000000000000000000000000000000000000000000000000000000000000000000000000000000000000000001000000000000000000000000000000000000000000000000000000000000000000000000000000000000000000000000000000000000000000000000000000010000000000000000000000000000000000000000000000000000000000000000000000000000000000000000000000000000000000000000000000000000000001000000000000000000000000000000000000000000000000000000000000101000000000000000000000000000000000000000000000000000000000000000000000000000000000000000000000000000000000000000000000000000000000 .
b10000111 D
1U
#20
0U
#21
b00000000000000000000000000001011 %
b10101010000000000000000000000111 )
b00000111 L
b00000000000000000000000000101100 T
1U
#22
0U
#23
b00000000000000000000000000001100 %
0,
1U
#24
0U
#25
b00000000000000000000000000001101 %
b10101010000000000000000000000111 &
b00000000000000000000000000110000 '
1,
b00000000000000000000000000001100 -
b00000000000000000000000000000000000000000000000000000000000000000000000000000000000000000000000000000000000000000000000000110000000000000000000000000000000000000000000000000000000000000000000000000000000000000000000000000000000000000000000000000000000001000000000000000000000000000000000000000000000000000000000000000000000000000000000000000000000000000000000000000000000000000000010000000000000000000000000000000000000000000000000000000000000000000000000000000000000000000000000000000000000000000000000000000001000000000000000000000000000000000000000000000000000000000000101000000000000000000000000000000000000000000000000000000000000000000000000000000000000000000000000000000000000000000000000000000000 .
b00000111 D
1U
#26
0U
#27
b00000000000000000000000000001110 %
b10101010000000000000000011011000 )
b11011000 L
b00000000000000000000000000110000 T
1U
#28
0U
#29
b00000000000000000000000000001111 %
0,
1U
#30
0U
#31
b00000000000000000000000000010000 %
b11111111000000000000000000110100 &
b00000000000000000000000000110100 '
1(
1,
b00000000000000000000000000001111 -
b00000000000000000000000000000000000000000000000000000000000000000000000000000000000000000000000000000000000000000000000000110100000000000000000000000000000000000000000000000000000000000000000100000000000000000000000000000000000000000000000000000000000001000000000000000000000000000000000000000000000000000000000000000000000000000000000000000000000000000000000000000000000000000000010000000000000000000000000000000000000000000000000000000000000000000000000000000000000000000000000000000000000000000000000000000001000000000000000000000000000000000000000000000000000000000000101000000000000000000000000000000000000000000000000000000000000000000000000000000000000000000000000000000000000000000000000000000000 .
b00110100 D
b11111111 G
1U
#32
0U
#33
b00000000000000000000000000010001 %
b11111111000000000000000000110100 )
b00110100 L
b11111111 O
b00000000000000000000000000110100 T
1U
#34
0U
#35
b00000000000000000000000000010010 %
0(
0,
1U
#36
0U
#37
b00000000000000000000000000010011 %
b00000000000000000000000000111000 '
1,
b00000000000000000000000000010010 -
b00000000000000000000000000000000000000000000000000000000000000000000000000000000000000000000000000000000000000000000000000111000000000000000000000000000000000000000000000000000000000000000000000000000000000000000000000000000000000000000000000000000000001000000000000000000000000000000000000000000000000000000000000000000000000000000000000000000000000000000000000000000000000000000010000000000000000000000000000000000000000000000000000000000000000000000000000000000000000000000000000000000000000000000000000000001000000000000000000000000000000000000000000000000000000000000101000000000000000000000000000000000000000000000000000000000000000000000000000000000000000000000000000000000000000000000000000000000 .
1U
#38
0U
#39
b00000000000000000000000000010100 %
b10101010000000000000000001101110 )
b01101110 L
b10101010 O
b00000000000000000000000000111000 T
1U
#40
0U
#41
b00000000000000000000000000010101 %
0,
1U
#42
0U
#43
b00000000000000000000000000010110 %
b10101010000000000000000001101110 &
b00000000000000000000000000111100 '
1,
b00000000000000000000000000010101 -
b00000000000000000000000000000000000000000000000000000000000000000000000000000000000000000000000000000000000000000000000000111100000000000000000000000000000000000000000000000000000000000000000000000000000000000000000000000000000000000000000000000000000001000000000000000000000000000000000000000000000000000000000000000000000000000000000000000000000000000000000000000000000000000000010000000000000000000000000000000000000000000000000000000000000000000000000000000000000000000000000000000000000000000000000000000001000000000000000000000000000000000000000000000000000000000000101000000000000000000000000000000000000000000000000000000000000000000000000000000000000000000000000000000000000000000000000000000000 .
b01101110 D
b10101010 G
1U
#44
0U
#45
b00000000000000000000000000010111 %
b10101010000000000000000011011101 )
b11011101 L
b00000000000000000000000000111100 T
1U
#46
0U
#47
b00000000000000000000000000011000 %
0,
1U
#48
0U
#49
b00000000000000000000000000011001 %
b10101010000000000000000011011101 &
b00000000000000000000000001000000 '
1,
b00000000000000000000000000011000 -
b00000000000000000000000000000000000000000000000000000000000000000000000000000000000000000000000000000000000000000000000001000000000000000000000000000000000000000000000000000000000000000000000000000000000000000000000000000000000000000000000000000000000001000000000000000000000000000000000000000000000000000000000000000000000000000000000000000000000000000000000000000000000000000000010000000000000000000000000000000000000000000000000000000000000000000000000000000000000000000000000000000000000000000000000000000001000000000000000000000000000000000000000000000000000000000000101000000000000000000000000000000000000000000000000000000000000000000000000000000000000000000000000000000000000000000000000000000000 .
b11011101 D
1U
#50
0U
#51
b00000000000000000000000000011010 %
b10101010000000000000000000100010 )
b00100010 L
b00000000000000000000000001000000 T
1U
#52
0U
#53
b00000000000000000000000000011011 %
0,
1U
#54
0U
#55
b00000000000000000000000000011100 %
b10101010000000000000000000100010 &
b00000000000000000000000001000100 '
1,
b00000000000000000000000000011011 -
b00000000000000000000000000000000000000000000000000000000000000000000000000000000000000000000000000000000000000000000000001000100000000000000000000000000000000000000000000000000000000000000000000000000000000000000000000000000000000000000000000000000000001000000000000000000000000000000000000000000000000000000000000000000000000000000000000000000000000000000000000000000000000000000010000000000000000000000000000000000000000000000000000000000000000000000000000000000000000000000000000000000000000000000000000000001000000000000000000000000000000000000000000000000000000000000101000000000000000000000000000000000000000000000000000000000000000000000000000000000000000000000000000000000000000000000000000000000 .
b00100010 D
1U
#56
0U
#57
b00000000000000000000000000011101 %
b10101010000000000000000001011111 )
b01011111 L
b00000000000000000000000001000100 T
1U
#58
0U
#59
b00000000000000000000000000011110 %
0,
1U
#60
0U
#61
b00000000000000000000000000011111 %
b10101010000000000000000001011111 &
b00000000000000000000000001001000 '
1,
b00000000000000000000000000011110 -
b00000000000000000000000000000000000000000000000000000000000000000000000000000000000000000000000000000000000000000000000001001000000000000000000000000000000000000000000000000000000000000000000000000000000000000000000000000000000000000000000000000000000001000000000000000000000000000000000000000000000000000000000000000000000000000000000000000000000000000000000000000000000000000000010000000000000000000000000000000000000000000000000000000000000000000000000000000000000000000000000000000000000000000000000000000001000000000000000000000000000000000000000000000000000000000000101000000000000000000000000000000000000000000000000000000000000000000000000000000000000000000000000000000000000000000000000000000000 .
b01011111 D
1U
#62
0U
#63
b00000000000000000000000000100000 %
b10101010000000000000000000010111 )
b00010111 L
b00000000000000000000000001001000 T
1U
#64
0U
#65
b00000000000000000000000000100001 %
0,
1U
#66
0U
#67
b00000000000000000000000000100010 %
b11111111000000000000000001001100 &
b00000000000000000000000001001100 '
1(
1,
b00000000000000000000000000100001 -
b00000000000000000000000000000000000000000000000000000000000000000000000000000000000000000000000000000000000000000000000001001100000000000000000000000000000000000000000000000000000000000000000100000000000000000000000000000000000000000000000000000000000001000000000000000000000000000000000000000000000000000000000000000000000000000000000000000000000000000000000000000000000000000000010000000000000000000000000000000000000000000000000000000000000000000000000000000000000000000000000000000000000000000000000000000001000000000000000000000000000000000000000000000000000000000000101000000000000000000000000000000000000000000000000000000000000000000000000000000000000000000000000000000000000000000000000000000000 .
b01001100 D
b11111111 G
1U
#68
0U
#69
b00000000000000000000000000100011 %
b11111111000000000000000001001100 )
b01001100 L
b11111111 O
b00000000000000000000000001001100 T
1U
#70
0U
#71
b00000000000000000000000000100100 %
0(
0,
1U
#72
0U
#73
b00000000000000000000000000100101 %
b00000000000000000000000001010000 '
1,
b00000000000000000000000000100100 -
b00000000000000000000000000000000000000000000000000000000000000000000000000000000000000000000000000000000000000000000000001010000000000000000000000000000000000000000000000000000000000000000000000000000000000000000000000000000000000000000000000000000000001000000000000000000000000000000000000000000000000000000000000000000000000000000000000000000000000000000000000000000000000000000010000000000000000000000000000000000000000000000000000000000000000000000000000000000000000000000000000000000000000000000000000000001000000000000000000000000000000000000000000000000000000000000101000000000000000000000000000000000000000000000000000000000000000000000000000000000000000000000000000000000000000000000000000000000 .
1U
#74
0U
#75
b00000000000000000000000000100110 %
b10101010000000000000000010111011 )
b10111011 L
b10101010 O
b00000000000000000000000001010000 T
1U
#76
0U
#77
b00000000000000000000000000100111 %
0,
1U
#78
0U
#79
b00000000000000000000000000101000 %
b10101010000000000000000010111011 &
b00000000000000000000000001010100 '
1,
b00000000000000000000000000100111 -
b00000000000000000000000000000000000000000000000000000000000000000000000000000000000000000000000000000000000000000000000001010100000000000000000000000000000000000000000000000000000000000000000000000000000000000000000000000000000000000000000000000000000001000000000000000000000000000000000000000000000000000000000000000000000000000000000000000000000000000000000000000000000000000000010000000000000000000000000000000000000000000000000000000000000000000000000000000000000000000000000000000000000000000000000000000001000000000000000000000000000000000000000000000000000000000000101000000000000000000000000000000000000000000000000000000000000000000000000000000000000000000000000000000000000000000000000000000000 .
b10111011 D
b10101010 G
1U
#80
0U
#81
b00000000000000000000000000101001 %
b10101010000000000000000011101001 )
b11101001 L
b00000000000000000000000001010100 T
1U
#82
0U
#83
b00000000000000000000000000101010 %
0,
1U
#84
0U
#85
b00000000000000000000000000101011 %
b10101010000000000000000011101001 &
b00000000000000000000000001011000 '
1,
b00000000000000000000000000101010 -
b00000000000000000000000000000000000000000000000000000000000000000000000000000000000000000000000000000000000000000000000001011000000000000000000000000000000000000000000000000000000000000000000000000000000000000000000000000000000000000000000000000000000001000000000000000000000000000000000000000000000000000000000000000000000000000000000000000000000000000000000000000000000000000000010000000000000000000000000000000000000000000000000000000000000000000000000000000000000000000000000000000000000000000000000000000001000000000000000000000000000000000000000000000000000000000000101000000000000000000000000000000000000000000000000000000000000000000000000000000000000000000000000000000000000000000000000000000000 .
b11101001 D
1U
#86
0U
#87
b00000000000000000000000000101100 %
b10101010000000000000000010011001 )
b10011001 L
b00000000000000000000000001011000 T
1U
#88
0U
#89
b00000000000000000000000000101101 %
0,
1U
#90
0U
#91
b00000000000000000000000000101110 %
b10101010000000000000000010011001 &
b00000000000000000000000001011100 '
1,
b00000000000000000000000000101101 -
b00000000000000000000000000000000000000000000000000000000000000000000000000000000000000000000000000000000000000000000000001011100000000000000000000000000000000000000000000000000000000000000000000000000000000000000000000000000000000000000000000000000000001000000000000000000000000000000000000000000000000000000000000000000000000000000000000000000000000000000000000000000000000000000010000000000000000000000000000000000000000000000000000000000000000000000000000000000000000000000000000000000000000000000000000000001000000000000000000000000000000000000000000000000000000000000101000000000000000000000000000000000000000000000000000000000000000000000000000000000000000000000000000000000000000000000000000000000 .
b10011001 D
1U
#92
0U
#93
b00000000000000000000000000101111 %
b10101010000000000000000001101110 )
b01101110 L
b00000000000000000000000001011100 T
1U
#94
0U
#95
b00000000000000000000000000110000 %
0,
1U
#96
0U
#97
b00000000000000000000000000110001 %
1*
0+
b00000000000000000000000000110000 -
b00000000000000000000000000000000000000000000000000000000000000000000000000000000000000000000000000000000000000000000000000000000000000000000000000000000000000000000000000000000000000000000001100000000000000000000000000000000000000000000000000000000000000000000000000000000000000000000000000000000000000000000000000000000000000000000000000000000000000000000000000000000000000000000000000000000000000000000000000000000000000000000000000000000000000000000000000000000000000000000000000000000000000000000000000000001000000000000000000000000000000000000000000000000000000000000000000000000000000000000000000000000000000000000000000000000000000000000000000000000000000000000000000000000000000000000000000000000 .
1U
